[
  {
    "name": "RMS Rhone",
    "lat": 18.3733,
    "lon": -64.6269,
    "osm_id": null,
    "osm_type": null,
    "depth": 26,
    "site_type": "wreck",
    "entry_type": "boat",
    "difficulty": "Intermediate",
    "validated": true,
    "validation_source": "Blue Water Divers, DiveBVI.com, PADI dive site guides",
    "tags": {
      "source": "curated",
      "addedBy": "gap_fill",
      "notes": "Maximum depth 26m (85ft). Bow at 24m, stern at 9m. Very open wreck with few entrapment hazards. World-class Caribbean wreck dive."
    }
  },
  {
    "name": "The Indians",
    "lat": 18.4333,
    "lon": -64.5167,
    "osm_id": null,
    "osm_type": null,
    "depth": 35,
    "site_type": "reef",
    "entry_type": "boat",
    "difficulty": "Beginner",
    "validated": true,
    "validation_source": "ScubaBoard BVI diving discussions, dive operator sites",
    "tags": {
      "source": "curated",
      "addedBy": "gap_fill",
      "notes": "Four rocky pinnacles. Shallow side 3m coral garden, deeper side steep wall to 11m. Excellent marine life including snapper, dolphins, turtles. Can have strong currents."
    }
  },
  {
    "name": "The Caves at Norman Island",
    "lat": 18.3167,
    "lon": -64.6167,
    "osm_id": null,
    "osm_type": null,
    "depth": 9,
    "site_type": "cave",
    "entry_type": "boat",
    "difficulty": "Beginner",
    "validated": true,
    "validation_source": "BVI-Dive-Map.com, epic yacht charters, local dive guides",
    "tags": {
      "source": "curated",
      "addedBy": "gap_fill",
      "notes": "Three water-level caves at Norman Island. First cave extends ~27m. Popular for snorkeling and shallow diving. Great for beginners and snorkelers."
    }
  },
  {
    "name": "Santa Monica Rock",
    "lat": 18.35,
    "lon": -64.6333,
    "osm_id": null,
    "osm_type": null,
    "depth": 31,
    "site_type": "pinnacle",
    "entry_type": "boat",
    "difficulty": "Advanced",
    "validated": true,
    "validation_source": "BVI-Dive-Map.com, BVIDiving.com, Blue Water Divers",
    "tags": {
      "source": "curated",
      "addedBy": "gap_fill",
      "notes": "Deepwater pinnacle 1.5km SE of Norman Island. Depths 6-31m. Craggy top with fire coral. Distinctive 'sink hole' feature. Pelagic fish and sharks. Watch for heavy fire coral."
    }
  },
  {
    "name": "Blonde Rock",
    "lat": 18.36,
    "lon": -64.62,
    "osm_id": null,
    "osm_type": null,
    "depth": 20,
    "site_type": "pinnacle",
    "entry_type": "boat",
    "difficulty": "Advanced",
    "validated": true,
    "validation_source": "BVIDiving.com, Sail Caribbean Divers, dive operator sites",
    "tags": {
      "source": "curated",
      "addedBy": "gap_fill",
      "notes": "Shallow pinnacle between Salt Island and Dead Chest Island. Rises from 18m to 5m. Complex system of tunnels, overhangs, undercuts. Abundant lobsters. Weather-dependent."
    }
  },
  {
    "name": "Alice in Wonderland",
    "lat": 18.4,
    "lon": -64.4333,
    "osm_id": null,
    "osm_type": null,
    "depth": 21,
    "site_type": "reef",
    "entry_type": "boat",
    "difficulty": "Beginner",
    "validated": true,
    "validation_source": "BVI-Dive-Map.com, Wannadive.net, dive operator guides",
    "tags": {
      "source": "curated",
      "addedBy": "gap_fill",
      "notes": "Off Ginger Island south shore. Spur and groove reef 11-21m. Outstanding visibility. Mushroom-shaped coral formations. Eagle rays, stingrays, turtles common. Easy navigation."
    }
  },
  {
    "name": "Wreck Alley",
    "lat": 18.45,
    "lon": -64.6167,
    "osm_id": null,
    "osm_type": null,
    "depth": 27,
    "site_type": "wreck",
    "entry_type": "boat",
    "difficulty": "Intermediate",
    "validated": true,
    "validation_source": "PADI Dive Site guides, ZuBlu, BVIDiving.com, Reef Smart Guides",
    "tags": {
      "source": "curated",
      "addedBy": "gap_fill",
      "notes": "Four scuttled wrecks (Pat, Beata, Mary L, Island Seal) off Cooper Island. Depths ~27m. Garden eels, rays, snappers, groupers, moray eels. Thriving artificial reef."
    }
  },
  {
    "name": "Anegada Reef",
    "lat": 18.7167,
    "lon": -64.3833,
    "osm_id": null,
    "osm_type": null,
    "depth": 10,
    "site_type": "reef",
    "entry_type": "boat",
    "difficulty": "Beginner",
    "validated": true,
    "validation_source": "PADI dive guides, Dive and Cruise, DiveScore",
    "tags": {
      "source": "curated",
      "addedBy": "gap_fill",
      "notes": "Part of 29km Horseshoe Reef - largest barrier reef in Caribbean. Pristine reefs, nurse sharks, rays, turtles. Access limited to those with local guide due to shallow and coral-dense conditions."
    }
  },
  {
    "name": "The Chimney at Great Dog Island",
    "lat": 18.4833,
    "lon": -64.4833,
    "osm_id": null,
    "osm_type": null,
    "depth": 12,
    "site_type": "cave",
    "entry_type": "boat",
    "difficulty": "Beginner",
    "validated": true,
    "validation_source": "BVIDiving.com, BVI-Dive-Map.com, Caribbean Dive Guide",
    "tags": {
      "source": "curated",
      "addedBy": "gap_fill",
      "notes": "Two rocky formations create a chimney gap. Protected northwest of Great Dog Island. Depths 9-12m. Shrimps, damselfish, parrotfish, scorpionfish. Famous Jacques Cousteau site."
    }
  },
  {
    "name": "Dry Rocks East",
    "lat": 18.3833,
    "lon": -64.5833,
    "osm_id": null,
    "osm_type": null,
    "depth": 24,
    "site_type": "reef",
    "entry_type": "boat",
    "difficulty": "Intermediate",
    "validated": true,
    "validation_source": "BVIDiving.com, Zentacle reviews, Dive Spot",
    "tags": {
      "source": "curated",
      "addedBy": "gap_fill",
      "notes": "East of Cooper Island. Ridge rises from 24m. Open water site with pillar corals, black corals, sea fans. Pelagic fish (cobia, African pompano). Can have strong currents - heed dive briefing."
    }
  },
  {
    "name": "Ginger Steps",
    "lat": 18.35,
    "lon": -64.55,
    "osm_id": null,
    "osm_type": null,
    "depth": 29,
    "site_type": "wall",
    "entry_type": "boat",
    "difficulty": "Intermediate",
    "validated": true,
    "validation_source": "PADI guides, BVI-Dive-Map.com, BVIDiving.com",
    "tags": {
      "source": "curated",
      "addedBy": "gap_fill",
      "notes": "Three dramatic step walls on Ginger Island southwest: 12m, 20m, 29m. Tube sponges, sea fans, corals. Protected from currents. White sand reflects sunlight creating magical scenery. Suitable for all levels."
    }
  },
  {
    "name": "Playgrounds Anegada",
    "lat": 18.7333,
    "lon": -64.3667,
    "osm_id": null,
    "osm_type": null,
    "depth": 8,
    "site_type": "reef",
    "entry_type": "boat",
    "difficulty": "Beginner",
    "validated": true,
    "validation_source": "PADI dive guides, Anegada diving information",
    "tags": {
      "source": "curated",
      "addedBy": "gap_fill",
      "notes": "Shallow reef site around Anegada. Part of pristine Horseshoe Reef system. Excellent for beginner divers. Requires local guide access due to shallow waters and coral maze characteristics."
    }
  },
  {
    "name": "Angelfish Reef",
    "lat": 18.310323,
    "lon": -64.628194,
    "osm_id": null,
    "osm_type": null,
    "depth": 27,
    "site_type": "reef",
    "entry_type": "boat",
    "difficulty": "Beginner",
    "validated": true,
    "validation_source": "bvi-dive-map.com",
    "tags": {
      "source": "curated",
      "addedBy": "gap_fill",
      "notes": "Southwest of Norman Island. Captivating canyons and ridges with gorgonians. Marine life includes jacks, drums, blennies, angelfish, seahorses, jawfish, turtles, rays, and nurse sharks."
    }
  },
  {
    "name": "Bronco Billy",
    "lat": 18.492992,
    "lon": -64.460067,
    "osm_id": null,
    "osm_type": null,
    "depth": 15,
    "site_type": "reef",
    "entry_type": "boat",
    "difficulty": "Intermediate",
    "validated": true,
    "validation_source": "bvi-dive-map.com",
    "tags": {
      "source": "curated",
      "addedBy": "gap_fill",
      "notes": "Northwestern tip of George Dog, allegedly favored by Jacques Cousteau. Features ridges, archways, canyons with soft and pillar coral. Limited visibility; flashlights recommended."
    }
  },
  {
    "name": "Carrot Shoal",
    "lat": 18.326619,
    "lon": -64.578413,
    "osm_id": null,
    "osm_type": null,
    "depth": 18,
    "site_type": "pinnacle",
    "entry_type": "boat",
    "difficulty": "Intermediate",
    "validated": true,
    "validation_source": "bvi-dive-map.com",
    "tags": {
      "source": "curated",
      "addedBy": "gap_fill",
      "notes": "Between Norman Island and Peter Island. Two pinnacles in open water. One of the most exciting night dive sites in the BVI. Named after neighboring Carrot Rock."
    }
  },
  {
    "name": "Dead Chest West",
    "lat": 18.362653,
    "lon": -64.564949,
    "osm_id": null,
    "osm_type": null,
    "depth": 17,
    "site_type": "reef",
    "entry_type": "boat",
    "difficulty": "Intermediate",
    "validated": true,
    "validation_source": "bvi-dive-map.com",
    "tags": {
      "source": "curated",
      "addedBy": "gap_fill",
      "notes": "West side of Dead Chest Island. Multi-level formations with overhangs, caves, ridges, passages, and archways. Snappers, fairy basslets, glassy sweepers, green moray eels, lobsters."
    }
  },
  {
    "name": "Ginger's Backside",
    "lat": 18.388521,
    "lon": -64.487552,
    "osm_id": null,
    "osm_type": null,
    "depth": 21,
    "site_type": "reef",
    "entry_type": "boat",
    "difficulty": "Intermediate",
    "validated": true,
    "validation_source": "bvi-dive-map.com",
    "tags": {
      "source": "curated",
      "addedBy": "gap_fill",
      "notes": "Northern side of Ginger Island in Sir Francis Drake Channel. Crabs, lobsters, octopuses, turtles, barracuda, nurse and reef sharks, tarpons, moray eels. Good for macro photography."
    }
  },
  {
    "name": "Devil's Kitchen",
    "lat": 18.375082,
    "lon": -64.50017,
    "osm_id": null,
    "osm_type": null,
    "depth": 15,
    "site_type": "wall",
    "entry_type": "boat",
    "difficulty": "Advanced",
    "validated": true,
    "validation_source": "bvi-dive-map.com",
    "tags": {
      "source": "curated",
      "addedBy": "gap_fill",
      "notes": "Hidden gem with a fiery red wall and rocky formations covered with corals and sponges. Parrotfish, grunts, turtles, lobsters, tarpons. Experiences big swells."
    }
  },
  {
    "name": "Flintstones",
    "lat": 18.485178,
    "lon": -64.473456,
    "osm_id": null,
    "osm_type": null,
    "depth": 20,
    "site_type": "reef",
    "entry_type": "boat",
    "difficulty": "Advanced",
    "validated": true,
    "validation_source": "bvi-dive-map.com",
    "tags": {
      "source": "curated",
      "addedBy": "gap_fill",
      "notes": "West of West Dog Island. Underwater boulders resembling Bedrock. Rocky formations with ledges and crevices. Snappers, gold-spotted eels, cobias, lobsters, eagle rays, nurse sharks."
    }
  },
  {
    "name": "Markoe Point",
    "lat": 18.38339,
    "lon": -64.47133,
    "osm_id": null,
    "osm_type": null,
    "depth": 20,
    "site_type": "reef",
    "entry_type": "boat",
    "difficulty": "Advanced",
    "validated": true,
    "validation_source": "bvi-dive-map.com",
    "tags": {
      "source": "curated",
      "addedBy": "gap_fill",
      "notes": "South of Cooper Island. Relatively uncrowded. Black durgons, snappers, jacks, groupers, mackerels, pompanos, spadefish, barracuda, lobsters. Good for underwater photography."
    }
  },
  {
    "name": "Painted Walls",
    "lat": 18.361676,
    "lon": -64.560314,
    "osm_id": null,
    "osm_type": null,
    "depth": 18,
    "site_type": "wall",
    "entry_type": "boat",
    "difficulty": "Intermediate",
    "validated": true,
    "validation_source": "bvi-dive-map.com",
    "tags": {
      "source": "curated",
      "addedBy": "gap_fill",
      "notes": "Near Dead Chest Island. Most vivid, picturesque dive site in the BVI. Four gullies with canyons, walls, and a narrow cave. Bold yellow, red, orange, purple corals. Hawksbill turtles, nurse sharks."
    }
  },
  {
    "name": "Paul's Grotto",
    "lat": 18.504144,
    "lon": -64.416388,
    "osm_id": null,
    "osm_type": null,
    "depth": null,
    "site_type": "cave",
    "entry_type": "boat",
    "difficulty": "Intermediate",
    "validated": true,
    "validation_source": "bvi-dive-map.com",
    "tags": {
      "source": "curated",
      "addedBy": "gap_fill",
      "notes": "Near Mountain Point and Cow's Mouth. Stunning underwater caves and hills covered in corals and gorgonians. Fire coral, staghorn, elkhorn, cup coral. Arrow crabs, fairy basslets, lobsters, lionfish, turtles."
    }
  },
  {
    "name": "The Visibles",
    "lat": 18.492015,
    "lon": -64.45835,
    "osm_id": null,
    "osm_type": null,
    "depth": null,
    "site_type": "pinnacle",
    "entry_type": "boat",
    "difficulty": "Beginner",
    "validated": true,
    "validation_source": "bvi-dive-map.com",
    "tags": {
      "source": "curated",
      "addedBy": "gap_fill",
      "notes": "Southwestern BVI, 12 minutes from Spanish Town. Massive pinnacle with caves, canyons, ledges. Glassy sweepers, tarpons, permits, barracudas, spadefish, turtles, eagle rays, reef sharks. Best in summer."
    }
  },
  {
    "name": "West Seal Dog",
    "lat": 18.505446,
    "lon": -64.437631,
    "osm_id": null,
    "osm_type": null,
    "depth": 28,
    "site_type": "cave",
    "entry_type": "boat",
    "difficulty": "Advanced",
    "validated": true,
    "validation_source": "bvi-dive-map.com",
    "tags": {
      "source": "curated",
      "addedBy": "gap_fill",
      "notes": "Uninhabited islet between Tortola and Virgin Gorda, part of Dog Islands group. National park since 1974. Caves, ledges, rocky formations covered with colorful sponges and corals. Secluded."
    }
  },
  {
    "name": "Blackbeard's",
    "lat": 18.369333,
    "lon": -64.563232,
    "osm_id": null,
    "osm_type": null,
    "depth": 15,
    "site_type": "reef",
    "entry_type": "boat",
    "difficulty": "Beginner",
    "validated": true,
    "validation_source": "bvi-dive-map.com",
    "tags": {
      "source": "curated",
      "addedBy": "gap_fill",
      "notes": "Northeast of Dead Chest Island. Brain, sheet, and star corals, large sea fans. Puffer fish, filefish, chub, snappers, goatfish, damselfish, squirrelfish, jawfish, barracuda."
    }
  },
  {
    "name": "Brewer's East",
    "lat": 18.448787,
    "lon": -64.653486,
    "osm_id": null,
    "osm_type": null,
    "depth": 21,
    "site_type": "reef",
    "entry_type": "boat",
    "difficulty": "Advanced",
    "validated": true,
    "validation_source": "bvi-dive-map.com",
    "tags": {
      "source": "curated",
      "addedBy": "gap_fill",
      "notes": "Eastern side of Brewers Bay, northern Tortola. Isolated rocky formations on sandy bottom. Glassy sweepers, tarpons, southern stingrays, nurse sharks. Quieter alternative to popular sites."
    }
  },
  {
    "name": "Fearless and Willy T",
    "lat": 18.36271,
    "lon": -64.58588,
    "osm_id": null,
    "osm_type": null,
    "depth": 24,
    "site_type": "wreck",
    "entry_type": "boat",
    "difficulty": "Advanced",
    "validated": true,
    "validation_source": "bvi-dive-map.com",
    "tags": {
      "source": "curated",
      "addedBy": "gap_fill",
      "notes": "Two sunken ships. The Fearless is believed to be sister ship of Cousteau's Calypso. The Willy T was a floating bar/restaurant. Both wooden wrecks severely degraded - caution required. Fairy basslets, eagle rays, turtles."
    }
  },
  {
    "name": "Inganess Bay",
    "lat": 18.373453,
    "lon": -64.519567,
    "osm_id": null,
    "osm_type": null,
    "depth": 29,
    "site_type": "wreck",
    "entry_type": "boat",
    "difficulty": "Intermediate",
    "validated": true,
    "validation_source": "bvi-dive-map.com",
    "tags": {
      "source": "curated",
      "addedBy": "gap_fill",
      "notes": "136-foot island freighter deliberately sunk in 1996 by BVI Dive Operators Association. Rests upright on sand. Divers can investigate cargo hold and corridors. Lizardfish, snappers, grunts, stingrays."
    }
  },
  {
    "name": "The Aquarium",
    "lat": 18.432136,
    "lon": -64.44454,
    "osm_id": null,
    "osm_type": null,
    "depth": 9,
    "site_type": "reef",
    "entry_type": "boat",
    "difficulty": "Beginner",
    "validated": true,
    "validation_source": "bvi-dive-map.com",
    "tags": {
      "source": "curated",
      "addedBy": "gap_fill",
      "notes": "Between The Baths and Spanish Town, Virgin Gorda. Rocky formations, small caves, granite boulders from volcanic activity. Chromis, angelfish, parrotfish, moorish idols, moray eels, lobsters, stingrays, nurse sharks."
    }
  },
  {
    "name": "Wall to Wall",
    "lat": 18.481209,
    "lon": -64.474143,
    "osm_id": null,
    "osm_type": null,
    "depth": null,
    "site_type": "wall",
    "entry_type": "boat",
    "difficulty": "Beginner",
    "validated": true,
    "validation_source": "bvi-dive-map.com",
    "tags": {
      "source": "curated",
      "addedBy": "gap_fill",
      "notes": "Next to Joe's Cave on West Dog, southwest tip closest to Scrub Island. Novice-level wall dive with low swell and low current."
    }
  },
  {
    "name": "Seal Dogs East",
    "lat": 18.507481,
    "lon": -64.430764,
    "osm_id": null,
    "osm_type": null,
    "depth": null,
    "site_type": "reef",
    "entry_type": "boat",
    "difficulty": "Advanced",
    "validated": true,
    "validation_source": "bvi-dive-map.com",
    "tags": {
      "source": "curated",
      "addedBy": "gap_fill",
      "notes": "Small islet northwest of Virgin Gorda in The Dogs group. Rocky formations with ledges and crevices. Open waters with strong currents. Colorful exotic fish. Good for underwater photography."
    }
  },
  {
    "name": "Spyglass Wall",
    "lat": 18.325152,
    "lon": -64.603819,
    "osm_id": null,
    "osm_type": null,
    "depth": 18,
    "site_type": "wall",
    "entry_type": "boat",
    "difficulty": "Intermediate",
    "validated": true,
    "validation_source": "bvi-dive-map.com",
    "tags": {
      "source": "curated",
      "addedBy": "gap_fill",
      "notes": "1,500-foot-long wall on north side of Norman Island. Named after Spyglass Hill from Treasure Island. Sea fans, purple tube sponges. Fairy basslets, damselfish, tarpons, eagle rays, stingrays, turtles."
    }
  },
  {
    "name": "Carval Rock",
    "lat": 18.372801,
    "lon": -64.491844,
    "osm_id": null,
    "osm_type": null,
    "depth": 27,
    "site_type": "pinnacle",
    "entry_type": "boat",
    "difficulty": "Advanced",
    "validated": true,
    "validation_source": "bvi-dive-map.com",
    "tags": {
      "source": "curated",
      "addedBy": "gap_fill",
      "notes": "Between Cooper and Ginger Islands. Magnificent rocky formation with boulders densely populated by fish. Sharks, barracuda, moray eels, lobsters, amberjacks, groupers, spotted drums. Not heavily frequented."
    }
  },
  {
    "name": "Cow's Mouth",
    "lat": 18.504836,
    "lon": -64.415958,
    "osm_id": null,
    "osm_type": null,
    "depth": 15,
    "site_type": "reef",
    "entry_type": "boat",
    "difficulty": "Intermediate",
    "validated": true,
    "validation_source": "bvi-dive-map.com",
    "tags": {
      "source": "curated",
      "addedBy": "gap_fill",
      "notes": "Northwest side of Virgin Gorda near Mountain Point. Named after rock shaped like a cow's mouth. Great visibility up to 100 feet. Barracuda, eagle rays, jacks. Experienced divers can explore inside the rock formation."
    }
  },
  {
    "name": "Great Tobago",
    "lat": 18.450339,
    "lon": -64.832472,
    "osm_id": null,
    "osm_type": null,
    "depth": 50,
    "site_type": "reef",
    "entry_type": "boat",
    "difficulty": "Advanced",
    "validated": true,
    "validation_source": "bvi-dive-map.com",
    "tags": {
      "source": "curated",
      "addedBy": "gap_fill",
      "notes": "Six miles west of Jost Van Dyke. National Park with third largest seabird population in Caribbean. Over 15 diving sites around the islands. Mercurious Rock cave system. Strict no-anchor policy. Black corals."
    }
  },
  {
    "name": "The Invisibles",
    "lat": 18.527339,
    "lon": -64.340642,
    "osm_id": null,
    "osm_type": null,
    "depth": 20,
    "site_type": "pinnacle",
    "entry_type": "boat",
    "difficulty": "Advanced",
    "validated": true,
    "validation_source": "bvi-dive-map.com",
    "tags": {
      "source": "curated",
      "addedBy": "gap_fill",
      "notes": "North of Virgin Gorda. Submerged pinnacle rising to 4 feet from surface with no marker buoy. Colorful coral and sponges. Strong currents bring many fish. Only suitable for less experienced divers in calm weather."
    }
  },
  {
    "name": "Thumb Rock",
    "lat": 18.369543,
    "lon": -64.509268,
    "osm_id": null,
    "osm_type": null,
    "depth": 18,
    "site_type": "pinnacle",
    "entry_type": "boat",
    "difficulty": "Advanced",
    "validated": true,
    "validation_source": "bvi-dive-map.com",
    "tags": {
      "source": "curated",
      "addedBy": "gap_fill",
      "notes": "Near Wreck Alley. Massive underwater pinnacle resembling a thumb. Tarpons, French angelfish, queen angelfish, spotted drums, seahorses, lobsters, barracuda. Superior marine biodiversity. Excellent for photography."
    }
  },
  {
    "name": "Monkey Point",
    "lat": 18.463523,
    "lon": -64.568214,
    "osm_id": null,
    "osm_type": null,
    "depth": 9,
    "site_type": "reef",
    "entry_type": "boat",
    "difficulty": "Beginner",
    "validated": true,
    "validation_source": "bvi-dive-map.com",
    "tags": {
      "source": "curated",
      "addedBy": "gap_fill",
      "notes": "South of Guana Island with white sand beach. Aquarium-like waters with nice walls and smaller rocky formations. Grunts, yellowtail snappers, yellow jacks, turtles. Fish reportedly allow close approach."
    }
  },
  {
    "name": "Shark Point",
    "lat": 18.472479,
    "lon": -64.50118,
    "osm_id": null,
    "osm_type": null,
    "depth": 21,
    "site_type": "reef",
    "entry_type": "boat",
    "difficulty": "Advanced",
    "validated": true,
    "validation_source": "bvi-dive-map.com",
    "tags": {
      "source": "curated",
      "addedBy": "gap_fill",
      "notes": "Near Scrub Island. System of ledges at ~18m full of sea life. Monitor open water for rays and sharks. Small caves and canyons. Higher currents typical. Head east from mooring to access ledge system."
    }
  },
  {
    "name": "Rhone Reef",
    "lat": 18.367104,
    "lon": -64.532903,
    "osm_id": null,
    "osm_type": null,
    "depth": 21,
    "site_type": "reef",
    "entry_type": "boat",
    "difficulty": "Advanced",
    "validated": true,
    "validation_source": "bvi-dive-map.com",
    "tags": {
      "source": "curated",
      "addedBy": "gap_fill",
      "notes": "Near the RMS Rhone wreck. Magnificent colored reef with soft and hard corals. Colorful exotic fish, turtles, nurse sharks, occasional reef sharks. Rocky canyons and small crevices. Weather-independent but can have currents."
    }
  },
  {
    "name": "Ring Dove Rock",
    "lat": 18.325967,
    "lon": -64.62356,
    "osm_id": null,
    "osm_type": null,
    "depth": 18,
    "site_type": "reef",
    "entry_type": "boat",
    "difficulty": "Intermediate",
    "validated": true,
    "validation_source": "bvi-dive-map.com",
    "tags": {
      "source": "curated",
      "addedBy": "gap_fill",
      "notes": "Less crowded site ideal for looping around schools of fish. Giant barrel sponges, golden zoanthids, crinoids, gorgonians. Butterflyfish, rock beauties, bar jacks, yellowhead jawfish, moray eels, lobsters."
    }
  },
  {
    "name": "Dolphin Rocks",
    "lat": 18.495679,
    "lon": -64.454625,
    "osm_id": null,
    "osm_type": null,
    "depth": 15,
    "site_type": "reef",
    "entry_type": "boat",
    "difficulty": "Advanced",
    "validated": true,
    "validation_source": "bvi-dive-map.com",
    "tags": {
      "source": "curated",
      "addedBy": "gap_fill",
      "notes": "Northern side of George Dog. Eastern canyons, western ledges. Smaller pelagic fish including barracuda, bonitos, mackerels, tarpons. Weather-dependent; best in summer. Often overlooked."
    }
  },
  {
    "name": "Dead Chest",
    "lat": 18.366889,
    "lon": -64.566493,
    "osm_id": null,
    "osm_type": null,
    "depth": null,
    "site_type": "reef",
    "entry_type": "boat",
    "difficulty": "Beginner",
    "validated": true,
    "validation_source": "bvi-dive-map.com",
    "tags": {
      "source": "curated",
      "addedBy": "gap_fill",
      "notes": "Uninhabited National Park between Salt and Peter Island. Three diving zones: Coral Gardens, Dead Chest Wall, and Painted Walls. Named after pirate legend of Edward Teach (Blackbeard). Fairy basslets, grunts, snappers."
    }
  },
  {
    "name": "Vanishing Rock",
    "lat": 18.377723,
    "lon": -64.520746,
    "osm_id": null,
    "osm_type": null,
    "depth": 13,
    "site_type": "reef",
    "entry_type": "boat",
    "difficulty": "Beginner",
    "validated": true,
    "validation_source": "bvi-dive-map.com",
    "tags": {
      "source": "curated",
      "addedBy": "gap_fill",
      "notes": "Eastern side of Salt Island near Cooper Island. 'Sergeant Major City' and 'Sergeant Major Suburbs' pillar coral formations. Anemones, shrimps, squirrelfish, jawfish, moray eels, lobsters, nurse sharks. Near RMS Rhone."
    }
  },
  {
    "name": "Brown Pants",
    "lat": 18.316842,
    "lon": -64.590429,
    "osm_id": null,
    "osm_type": null,
    "depth": 12,
    "site_type": "cave",
    "entry_type": "boat",
    "difficulty": "Advanced",
    "validated": true,
    "validation_source": "bvi-dive-map.com",
    "tags": {
      "source": "curated",
      "addedBy": "gap_fill",
      "notes": "South of Norman Island. Maze of ledges, canyons, and caverns with an open cave. Queen angelfish, black durgon, barracuda, stingrays, lobsters, eels, sea turtles. Labyrinth of canyons and tunnels."
    }
  },
  {
    "name": "Rainbow Canyons",
    "lat": 18.330693,
    "lon": -64.626478,
    "osm_id": null,
    "osm_type": null,
    "depth": 18,
    "site_type": "reef",
    "entry_type": "boat",
    "difficulty": "Beginner",
    "validated": true,
    "validation_source": "bvi-dive-map.com",
    "tags": {
      "source": "curated",
      "addedBy": "gap_fill",
      "notes": "North of Norman Island near Pelican Island. Juvenile trunkfish, spotted drums, creole wrasse, garden eels, queen angelfish, nurse sharks. Abundant corals, sponges, gorgonians. Incredible photographic potential."
    }
  },
  {
    "name": "Randy's Reef",
    "lat": 18.358066,
    "lon": -64.591116,
    "osm_id": null,
    "osm_type": null,
    "depth": 24,
    "site_type": "reef",
    "entry_type": "boat",
    "difficulty": "Intermediate",
    "validated": true,
    "validation_source": "bvi-dive-map.com",
    "tags": {
      "source": "curated",
      "addedBy": "gap_fill",
      "notes": "East of Little Harbour. Deep water harbor with moorings. Large rays in front of beach club. Caution with local fishermen's nets in afternoon."
    }
  },
  {
    "name": "Rhone's Anchor",
    "lat": 18.361488,
    "lon": -64.58794,
    "osm_id": null,
    "osm_type": null,
    "depth": null,
    "site_type": "wreck",
    "entry_type": "boat",
    "difficulty": "Advanced",
    "validated": true,
    "validation_source": "bvi-dive-map.com",
    "tags": {
      "source": "curated",
      "addedBy": "gap_fill",
      "notes": "Between Fearless and Randy's Reef. Features the anchor from the RMS Rhone, lost on October 29, 1867 when the captain attempted to raise it during bad weather. Anchor covered in colorful coral growth. Blennies, wrasses, damselfish."
    }
  },
  {
    "name": "Chikuzen",
    "lat": 18.554844,
    "lon": -64.337157,
    "osm_id": null,
    "osm_type": null,
    "depth": 23,
    "site_type": "wreck",
    "entry_type": "boat",
    "difficulty": "Advanced",
    "validated": true,
    "validation_source": "bvi-dive-map.com",
    "tags": {
      "source": "curated",
      "addedBy": "gap_fill",
      "notes": "Between Tortola and Anegada. 246-foot refrigerated cargo vessel sunk 1981. Adorned with colorful corals and sponges. Horse-eyed jacks, jewfish, barracuda, cobia, groupers, stingrays, turtles, and a resident 600-pound Goliath grouper."
    }
  },
  {
    "name": "Cistern Point",
    "lat": 18.380132,
    "lon": -64.516992,
    "osm_id": null,
    "osm_type": null,
    "depth": 12,
    "site_type": "reef",
    "entry_type": "boat",
    "difficulty": "Intermediate",
    "validated": true,
    "validation_source": "bvi-dive-map.com",
    "tags": {
      "source": "curated",
      "addedBy": "gap_fill",
      "notes": "Western side of Cooper Island. Craters, ledges, rocky outcroppings with sea fans. Blue tangs, queen angelfish, snappers, grunts, tarpon, turtles, stingrays, moray eels, nurse sharks. Quieter than nearby sites."
    }
  },
  {
    "name": "Fallen Jerusalem",
    "lat": 18.42065,
    "lon": -64.452748,
    "osm_id": null,
    "osm_type": null,
    "depth": null,
    "site_type": "cave",
    "entry_type": "boat",
    "difficulty": "Advanced",
    "validated": true,
    "validation_source": "bvi-dive-map.com",
    "tags": {
      "source": "curated",
      "addedBy": "gap_fill",
      "notes": "Uninhabited island south of Virgin Gorda. National Park since 1974, bird sanctuary since 1959. Heavy volcanic boulders. Underwater caves, tunnels, and rocky formations."
    }
  },
  {
    "name": "Blue Chromis Reef",
    "lat": 18.374899,
    "lon": -64.510743,
    "osm_id": null,
    "osm_type": null,
    "depth": 27,
    "site_type": "reef",
    "entry_type": "boat",
    "difficulty": "Beginner",
    "validated": true,
    "validation_source": "bvi-dive-map.com",
    "tags": {
      "source": "curated",
      "addedBy": "gap_fill",
      "notes": "Named after the blue chromis fish. Sea fans, gorgonians, quillfin blennies on sandy seafloor. Depth range 9-27m. Straightforward layout, difficult to get lost. Good for training dives."
    }
  },
  {
    "name": "Coral Gardens",
    "lat": 18.480208,
    "lon": -64.456841,
    "osm_id": null,
    "osm_type": null,
    "depth": 15,
    "site_type": "wreck",
    "entry_type": "boat",
    "difficulty": "Beginner",
    "validated": true,
    "validation_source": "bvi-dive-map.com",
    "tags": {
      "source": "curated",
      "addedBy": "gap_fill",
      "notes": "Beautiful coral formations combined with an airplane wreck placed as part of BVI reef program. Aircraft lacks wings and tail but has become center of sea life. Lobsters, stingrays, barracuda, occasional turtles."
    }
  },
  {
    "name": "Gun Point",
    "lat": 18.394151,
    "lon": -64.701837,
    "osm_id": null,
    "osm_type": null,
    "depth": 6,
    "site_type": "reef",
    "entry_type": "shore",
    "difficulty": "Beginner",
    "validated": true,
    "validation_source": "bvi-dive-map.com",
    "tags": {
      "source": "curated",
      "addedBy": "gap_fill",
      "notes": "Hidden gem with uncrowded white sand beaches. Amazing offshore coral reef with colorful tropical fish. Great visibility due to shallow depths. Shore entry via dirt road."
    }
  },
  {
    "name": "Diamond Reef",
    "lat": 18.466373,
    "lon": -64.525727,
    "osm_id": null,
    "osm_type": null,
    "depth": 12,
    "site_type": "reef",
    "entry_type": "boat",
    "difficulty": "Intermediate",
    "validated": true,
    "validation_source": "bvi-dive-map.com",
    "tags": {
      "source": "curated",
      "addedBy": "gap_fill",
      "notes": "Off Great Camanoe, 2 minutes from Scrub Island. Soft and hard corals with colorful sponges. Sergeant majors, grey snappers, blue chromis, wrasses, parrotfish, garden eels, stingrays, turtles."
    }
  },
  {
    "name": "Brewers Pinnacle",
    "lat": 18.444864,
    "lon": -64.660046,
    "osm_id": null,
    "osm_type": null,
    "depth": 30,
    "site_type": "pinnacle",
    "entry_type": "boat",
    "difficulty": "Advanced",
    "validated": true,
    "validation_source": "bvi-dive-map.com",
    "tags": {
      "source": "curated",
      "addedBy": "gap_fill",
      "notes": "Western side of Brewers Bay, northern Tortola. Isolated rocky pinnacles rising to different heights. Baitfish, blennies, mackerel, tarpon, lobsters. Secluded site without crowds."
    }
  },
  {
    "name": "The Playground",
    "lat": 18.455875,
    "lon": -64.711622,
    "osm_id": null,
    "osm_type": null,
    "depth": 27,
    "site_type": "reef",
    "entry_type": "boat",
    "difficulty": "Advanced",
    "validated": true,
    "validation_source": "bvi-dive-map.com",
    "tags": {
      "source": "curated",
      "addedBy": "gap_fill",
      "notes": "East of Green Cay West near Little Jost Van Dyke. Corals and gorgonians with exciting pinnacles on north side. Angelfish, parrotfish, dog snappers, reef squids, manta rays, reef sharks, tarpons."
    }
  },
  {
    "name": "Mountain Point",
    "lat": 18.504754,
    "lon": -64.416688,
    "osm_id": null,
    "osm_type": null,
    "depth": 23,
    "site_type": "reef",
    "entry_type": "boat",
    "difficulty": "Beginner",
    "validated": true,
    "validation_source": "bvi-dive-map.com",
    "tags": {
      "source": "curated",
      "addedBy": "gap_fill",
      "notes": "Northwest of Virgin Gorda. Sandy bottom with corals and sea sponges. Caves, passages, rock formations with sleeping nurse sharks. Northern reef in excellent condition. Grunts, parrotfish, angelfish, tarpons, jacks, stingrays."
    }
  },
  {
    "name": "Joe's Cave",
    "lat": 18.481352,
    "lon": -64.475087,
    "osm_id": null,
    "osm_type": null,
    "depth": 14,
    "site_type": "cave",
    "entry_type": "boat",
    "difficulty": "Advanced",
    "validated": true,
    "validation_source": "bvi-dive-map.com",
    "tags": {
      "source": "curated",
      "addedBy": "gap_fill",
      "notes": "West of West Dog Island. Huge boulders up to 25 feet high on sandy bottom. Underwater cave narrow at top, widens at base. Giant groupers, lobsters, eagle rays, glassy sweepers. Colorful corals and sponges on cave walls."
    }
  }
]
