[
  {
    "name": "MuMart (museo sommerso)",
    "filename": "mumart-museo-sommerso.md",
    "lat": 40.9991561,
    "lng": 9.6124256,
    "difficulty": "Beginner",
    "maxDepth": 7,
    "entryType": "boat",
    "siteType": "reef",
    "ref": "",
    "osmId": 4840240367
  },
  {
    "name": "Cala Mariolu",
    "filename": "cala-mariolu.md",
    "lat": 40.1232825,
    "lng": 9.6767178,
    "difficulty": "Intermediate",
    "maxDepth": 18,
    "entryType": "boat",
    "siteType": "wall",
    "ref": "",
    "osmId": 184754084
  },
  {
    "name": "Nereo Cave",
    "filename": "nereo-cave.md",
    "lat": 40.56,
    "lng": 8.16,
    "difficulty": "Advanced",
    "maxDepth": 35,
    "entryType": "boat",
    "siteType": "cave",
    "ref": "",
    "osmId": null
  },
  {
    "name": "Capo Caccia Cliffs",
    "filename": "capo-caccia-cliffs.md",
    "lat": 40.57,
    "lng": 8.155,
    "difficulty": "Advanced",
    "maxDepth": 30,
    "entryType": "boat",
    "siteType": "wall",
    "ref": "",
    "osmId": null
  },
  {
    "name": "KT Wreck",
    "filename": "kt-wreck.md",
    "lat": 39.22,
    "lng": 9.12,
    "difficulty": "Advanced",
    "maxDepth": 34,
    "entryType": "boat",
    "siteType": "wreck",
    "ref": "",
    "osmId": null
  },
  {
    "name": "Tavolara Island",
    "filename": "tavolara-island.md",
    "lat": 40.89,
    "lng": 9.71,
    "difficulty": "Intermediate",
    "maxDepth": 25,
    "entryType": "boat",
    "siteType": "reef",
    "ref": "",
    "osmId": null
  },
  {
    "name": "Secca del Papa",
    "filename": "secca-del-papa.md",
    "lat": 40.9147,
    "lng": 9.7478,
    "difficulty": "Advanced",
    "maxDepth": 35,
    "entryType": "boat",
    "siteType": "pinnacle",
    "ref": "",
    "osmId": null
  },
  {
    "name": "Isola dei Cavoli",
    "filename": "isola-dei-cavoli.md",
    "lat": 39.08,
    "lng": 9.53,
    "difficulty": "Intermediate",
    "maxDepth": 40,
    "entryType": "boat",
    "siteType": "wall",
    "ref": "",
    "osmId": null
  },
  {
    "name": "Cala Gonone",
    "filename": "cala-gonone.md",
    "lat": 40.28,
    "lng": 9.64,
    "difficulty": "Intermediate",
    "maxDepth": 15,
    "entryType": "boat",
    "siteType": "cave",
    "ref": "",
    "osmId": null
  },
  {
    "name": "Villasimius Marine Park",
    "filename": "villasimius-marine-park.md",
    "lat": 39.15,
    "lng": 9.51,
    "difficulty": "Beginner",
    "maxDepth": 12,
    "entryType": "boat",
    "siteType": "reef",
    "ref": "",
    "osmId": null
  },
  {
    "name": "Porto Conte Reef",
    "filename": "porto-conte-reef.md",
    "lat": 40.58,
    "lng": 8.18,
    "difficulty": "Beginner",
    "maxDepth": 16,
    "entryType": "boat",
    "siteType": "reef",
    "ref": "",
    "osmId": null
  }
]
